LICENSE
MANIFEST.in
README.md
setup.py
src/webcandy/__init__.py
src/webcandy/app.py
src/webcandy/config.py
src/webcandy/definitions.py
src/webcandy/extensions.py
src/webcandy/models.py
src/webcandy/routes.py
src/webcandy/server.py
src/webcandy/util.py
src/webcandy.egg-info/PKG-INFO
src/webcandy.egg-info/SOURCES.txt
src/webcandy.egg-info/dependency_links.txt
src/webcandy.egg-info/not-zip-safe
src/webcandy.egg-info/requires.txt
src/webcandy.egg-info/top_level.txt