Metadata-Version: 2.1
Name: webcandy
Version: 0.0.2
Summary: API and web interface for Fadecandy
Home-page: https://webcandy.io
Author: Graham Preston
Author-email: graham.preston@gmail.com
License: UNKNOWN
Project-URL: Documentation, https://webcandy.readthedocs.io
Project-URL: Source, https://github.com/gcpreston/webcandy
Platform: UNKNOWN
Classifier: Development Status :: 3 - Alpha
Classifier: License :: OSI Approved :: MIT License
Classifier: Programming Language :: Python :: 3
Classifier: Programming Language :: Python :: 3.7
